mnemonic_encrypt/__init__.py
mnemonic_encrypt/__version__.py
mnemonic_encrypt/cli.py
mnemonic_encrypt/core.py
mnemonic_encrypt-0.1.0.dist-info/LICENSE
mnemonic_encrypt-0.1.0.dist-info/METADATA
mnemonic_encrypt-0.1.0.dist-info/WHEEL
mnemonic_encrypt-0.1.0.dist-info/entry_points.txt
mnemonic_encrypt-0.1.0.dist-info/top_level.txt
mnemonic_encrypt-0.1.0.dist-info/RECORD
