Metadata-Version: 2.1
Name: mnemonic-encrypt
Version: 0.1.0
Summary: 🔐 Secure cryptocurrency mnemonic phrase encryption tool powered by AnyEncrypt
Author-email: fOcusOnus <focusonus@example.com>
License: MIT
Project-URL: Homepage, https://github.com/fOcusOnus/mnemonic-encrypt
Project-URL: Documentation, https://github.com/fOcusOnus/mnemonic-encrypt#readme
Project-URL: Repository, https://github.com/fOcusOnus/mnemonic-encrypt
Project-URL: Issues, https://github.com/fOcusOnus/mnemonic-encrypt/issues
Keywords: mnemonic,encryption,cryptocurrency,bip39,wallet,security,anyencrypt,cli
Classifier: Development Status :: 4 - Beta
Classifier: Intended Audience :: Developers
Classifier: License :: OSI Approved :: MIT License
Classifier: Programming Language :: Python :: 3
Classifier: Programming Language :: Python :: 3.8
Classifier: Programming Language :: Python :: 3.9
Classifier: Programming Language :: Python :: 3.10
Classifier: Programming Language :: Python :: 3.11
Classifier: Programming Language :: Python :: 3.12
Classifier: Topic :: Security :: Cryptography
Classifier: Topic :: Software Development :: Libraries :: Python Modules
Requires-Python: >=3.8
License-File: LICENSE
Requires-Dist: anyencrypt>=0.4.0
Requires-Dist: mnemonic>=0.20
Requires-Dist: click>=8.0.0
Provides-Extra: dev
Requires-Dist: pytest>=7.0.0; extra == "dev"
Requires-Dist: pytest-cov>=4.0.0; extra == "dev"
Requires-Dist: black>=23.0.0; extra == "dev"
Requires-Dist: flake8>=6.0.0; extra == "dev"
Requires-Dist: mypy>=1.0.0; extra == "dev"
